{
  "replace": false,
  "values": [
    {"id": "inmis:ender_pouch", "required": false},
    {"id": "inmis:baby_backpack", "required": false},
    {"id": "inmis:frayed_backpack", "required": false},
    {"id": "inmis:plated_backpack", "required": false},
    {"id": "inmis:gilded_backpack", "required": false},
    {"id": "inmis:bejeweled_backpack", "required": false},
    {"id": "inmis:blazing_backpack", "required": false},
    {"id": "inmis:withered_backpack", "required": false},
    {"id": "inmis:endless_backpack", "required": false}
  ]
}